helical/__init__.py
helical/constants/__init__.py
helical/constants/enums.py
helical/constants/paths.py
helical/models/__init__.py
helical/models/base_models.py
helical/models/c2s/LICENSE
helical/models/c2s/README.md
helical/models/c2s/__init__.py
helical/models/c2s/config.py
helical/models/c2s/model.py
helical/models/caduceus/LICENSE
helical/models/caduceus/README.md
helical/models/caduceus/__init__.py
helical/models/caduceus/caduceus_config.py
helical/models/caduceus/caduceus_tokenizer.py
helical/models/caduceus/fine_tuning_model.py
helical/models/caduceus/model.py
helical/models/caduceus/modeling_caduceus.py
helical/models/caduceus/modeling_rcps.py
helical/models/caduceus/pretrained_config.py
helical/models/evo_2/Dockerfile
helical/models/evo_2/LICENSE
helical/models/evo_2/README.md
helical/models/evo_2/__init__.py
helical/models/evo_2/evo2_tokenizer.py
helical/models/evo_2/evo_2_config.py
helical/models/evo_2/model.py
helical/models/evo_2/scoring.py
helical/models/fine_tune/__init__.py
helical/models/fine_tune/fine_tuning_heads.py
helical/models/geneformer/LICENSE
helical/models/geneformer/README.md
helical/models/geneformer/__init__.py
helical/models/geneformer/fine_tuning_model.py
helical/models/geneformer/geneformer_config.py
helical/models/geneformer/geneformer_tokenizer.py
helical/models/geneformer/geneformer_utils.py
helical/models/geneformer/model.py
helical/models/genept/__init__.py
helical/models/genept/genept_config.py
helical/models/genept/model.py
helical/models/helix_mrna/LICENSE
helical/models/helix_mrna/README.md
helical/models/helix_mrna/__init__.py
helical/models/helix_mrna/fine_tuning_model.py
helical/models/helix_mrna/helix_mrna_config.py
helical/models/helix_mrna/helix_mrna_pretrained_config.py
helical/models/helix_mrna/helix_mrna_tokenizer.py
helical/models/helix_mrna/helix_mrna_utils.py
helical/models/helix_mrna/model.py
helical/models/helix_mrna/modeling_helix_mrna.py
helical/models/hyena_dna/LICENSE
helical/models/hyena_dna/README.md
helical-1.5.3.dist-info/METADATA
helical-1.5.3.dist-info/WHEEL
helical-1.5.3.dist-info/licenses/LICENSE
helical-1.5.3.dist-info/RECORD
