Metadata-Version: 2.4
Name: helical
Version: 1.5.3
Summary: Helical Python SDK
Project-URL: Homepage, https://github.com/helicalAI/helical
Project-URL: Issues, https://github.com/helicalAI/helical/issues
Project-URL: Documentation, https://helical.readthedocs.io/
Project-URL: Repository, https://github.com/helicalAI/helical
Author-email: Helical Team <support@helical-ai.com>
License:                     GNU AFFERO GENERAL PUBLIC LICENSE
License-File: LICENSE
Classifier: License :: OSI Approved :: GNU Affero General Public License v3 or later (AGPLv3+)
Classifier: Operating System :: OS Independent
Classifier: Programming Language :: Python :: 3
Requires-Python: >=3.9
Requires-Dist: accelerate==1.4.0
Requires-Dist: anndata>=0.11
Requires-Dist: bitsandbytes>=0.48.2
Requires-Dist: datasets==3.6.0
Requires-Dist: einops==0.8.1
Requires-Dist: gitpython==3.1.44
Requires-Dist: hydra-core==1.3.2
Requires-Dist: loompy==3.0.7
Requires-Dist: louvain==0.8.2
Requires-Dist: numpy<2.3,>=2.1.3
Requires-Dist: omegaconf==2.3.0
Requires-Dist: pandas==2.2.2
Requires-Dist: protobuf>=3.20.0
Requires-Dist: pybiomart
Requires-Dist: requests>=2.32.3
Requires-Dist: scib==1.1.5
Requires-Dist: scikit-learn>=1.5.0
Requires-Dist: scikit-misc>=0.5.2
Requires-Dist: scipy==1.13.1
Requires-Dist: sentencepiece>=0.2.0
Requires-Dist: torch==2.7.0
Requires-Dist: transformers<=4.51.3,>=4.49.0
Provides-Extra: evo-2
Requires-Dist: biopython==1.85; extra == 'evo-2'
Requires-Dist: transformer-engine[pytorch]==1.13.0; extra == 'evo-2'
Provides-Extra: mamba-ssm
Requires-Dist: causal-conv1d==1.5.1; extra == 'mamba-ssm'
Requires-Dist: mamba-ssm==2.2.5; extra == 'mamba-ssm'
